{
	"class" : {
		"Curvier" : "",
		"aaFontsColormapDepth" : "jmv 8/4/2009 15:09",
		"abbreviatedBrowserButtons" : "",
		"acceptAnnotationsFrom:" : "sw 2/24/1999 12:26",
		"addBooleanPreference:categories:default:balloonHelp:" : "ar 8/9/2009 15:14",
		"addBooleanPreference:categories:default:balloonHelp:projectLocal:changeInformee:changeSelector:" : "ar 8/9/2009 15:14",
		"addBooleanPreference:category:default:balloonHelp:" : "ar 8/9/2009 15:14",
		"addColorPreference:categories:default:balloonHelp:" : "ar 8/9/2009 15:15",
		"addColorPreference:category:default:balloonHelp:" : "ar 8/9/2009 15:15",
		"addFontPreference:categories:default:balloonHelp:" : "ar 8/9/2009 15:15",
		"addFontPreference:category:default:balloonHelp:" : "ar 8/9/2009 15:15",
		"addModelItemsToWindowMenu:" : "sw 10/6/1999 15:20",
		"addNumericPreference:categories:default:balloonHelp:" : "ar 8/9/2009 15:15",
		"addNumericPreference:category:default:balloonHelp:" : "ar 8/9/2009 15:15",
		"addPreference:categories:default:balloonHelp:" : "hpt 9/26/2004 16:05",
		"addPreference:categories:default:balloonHelp:projectLocal:changeInformee:changeSelector:" : "hpt 12/5/2004 13:29",
		"addPreference:categories:default:balloonHelp:projectLocal:changeInformee:changeSelector:type:" : "ar 8/9/2009 15:13",
		"addPreference:categories:default:balloonHelp:projectLocal:changeInformee:changeSelector:viewRegistry:" : "ar 8/9/2009 16:12",
		"addPreference:category:default:balloonHelp:" : "hpt 9/26/2004 16:05",
		"addTextPreference:categories:default:balloonHelp:" : "ar 8/9/2009 15:15",
		"addTextPreference:category:default:balloonHelp:" : "ar 8/9/2009 15:15",
		"allPreferenceObjects" : "rr 10/1/2005 15:14",
		"allowBlockArgumentAssignment" : "",
		"allowUnderscoreAssignment" : "",
		"alphabeticalProjectMenu" : "",
		"alternateHandlesLook" : "",
		"alternativeBrowseIt" : "",
		"alternativeButtonsInScrollBars" : "",
		"alternativeWindowBoxesLook" : "dgd 3/21/2003 19:23",
		"alwaysHideHScrollbar" : "",
		"alwaysShowConnectionVocabulary" : "",
		"alwaysShowHScrollbar" : "",
		"alwaysShowVScrollbar" : "",
		"annotationEditingWindow" : "tfel 3/27/2010 13:34",
		"annotationInfo" : "sw 7/12/2001 18:18",
		"annotationPanes" : "sbw 4/24/2010 10:16",
		"annotationPanesChanged" : "sw 6/12/2001 20:17",
		"areaFillsAreTolerant" : "",
		"areaFillsAreVeryTolerant" : "",
		"attemptToRestoreClassicFonts" : "nice 12/27/2009 03:11",
		"autoIndent" : "",
		"automaticFlapLayout" : "",
		"automaticFlapLayoutString" : "dgd 8/31/2003 18:07",
		"automaticKeyGeneration" : "",
		"automaticPlatformSettings" : "",
		"automaticViewerPlacement" : "",
		"balloonHelpDelayTime" : "dgd 9/7/2004 18:35",
		"balloonHelpEnabled" : "",
		"balloonHelpInMessageLists" : "",
		"batchPenTrails" : "",
		"bigDisplay" : "",
		"biggerHandles" : "",
		"borderColorWhenRunning" : "sw 2/15/1999 19:44",
		"browseThemes" : "ar 9/27/2005 21:07",
		"browseToolClass" : "ar 9/28/2005 15:04",
		"browseWithDragNDrop" : "",
		"browseWithPrettyPrint" : "",
		"browserShowsPackagePane" : "",
		"canRecordWhilePlaying" : "",
		"capitalizedReferences" : "",
		"caretWidth" : "lr 7/12/2006 09:25",
		"caretWidth:" : "lr 7/12/2006 09:25",
		"caseSensitiveFinds" : "",
		"categoriesContainingPreference:" : "sw 4/10/2001 14:29",
		"categoryNames" : "rr 10/1/2005 15:14",
		"cautionBeforeClosing" : "",
		"changeSetVersionNumbers" : "",
		"checkForSlips" : "",
		"checkForUnsavedProjects" : "",
		"checkForWindowColors" : "hpt 12/6/2004 22:49",
		"chooseBalloonHelpFont" : "bp 6/13/2004 17:20",
		"chooseCodeFont" : "tween 8/7/2007 01:59",
		"chooseEToysFont" : "tween 8/7/2007 02:00",
		"chooseEToysTitleFont" : "tween 8/7/2007 02:00",
		"chooseFlapsFont" : "tween 8/7/2007 02:00",
		"chooseFontWithPrompt:andSendTo:withSelector:highlightSelector:" : "ar 8/30/2009 16:44",
		"chooseHaloLabelFont" : "tween 8/7/2007 02:00",
		"chooseInitialSettings" : "sw 4/10/2001 15:28",
		"chooseInsertionPointColor" : "sw 9/6/2000 18:45",
		"chooseKeyboardFocusColor" : "sw 12/7/2001 00:44",
		"chooseListFont" : "tween 8/7/2007 02:01",
		"chooseMenuFont" : "tween 8/7/2007 02:01",
		"chooseStandardButtonFont" : "tween 8/7/2007 02:01",
		"chooseSystemFont" : "tween 8/7/2007 02:01",
		"chooseTextHighlightColor" : "sw 9/6/2000 18:45",
		"chooseWindowTitleFont" : "tween 8/7/2007 02:01",
		"classicHaloSpecs" : "sw 12/30/2004 01:42",
		"classicHalosInForce" : "hpt 9/24/2004 23:34",
		"classicNavigatorEnabled" : "",
		"classicTilesSettingToggled" : "em 3/24/2005 15:34",
		"cmdDotEnabled" : "",
		"cmdGesturesEnabled" : "programmatic 7/15/1999 09:55",
		"cmdKeysInText" : "programmatic 7/15/1999 09:55",
		"collapseWindowsInPlace" : "",
		"compactViewerFlaps" : "",
		"compileAccessMethodForPreference:" : "ul 5/22/2010 01:34",
		"compileHardCodedPref:enable:" : "ul 5/22/2010 01:33",
		"compressFlashImages" : "",
		"confirmFirstUseOfStyle" : "",
		"conversionMethodsAtFileOut" : "",
		"cpuWatcherEnabled" : "",
		"customHaloSpecs" : "laza 3/24/2000 16:05",
		"customHalosInForce" : "hpt 9/24/2004 23:34",
		"darkenStandardWindowPreferences" : "hpt 12/8/2004 19:34",
		"debugHaloHandle" : "",
		"debugLogTimestamp" : "mir 3/5/2004 19:22",
		"debugMenuItemsInvokableFromScripts" : "sw 12/1/1999 13:04",
		"debugPrintSpaceLog" : "",
		"debugShowDamage" : "",
		"decorateBrowserButtons" : "",
		"defaultAnnotationRequests" : "sw 2/17/1999 00:40",
		"defaultAnnotationRequests:" : "sw 2/8/1999 10:14",
		"defaultAuthorName" : "sma 6/1/2000 12:08",
		"defaultFileOutFormatMacRoman" : "",
		"defaultPaintingExtent" : "sw 2/1/2000 14:05",
		"defaultValueTableForCurrentRelease" : "rss 8/23/2009 11:03",
		"defaultWorldColor" : "dgd 9/5/2004 16:17",
		"desktopColor" : "jhm 10/15/97 17:31",
		"desktopColor:" : "jhm 10/15/97 17:31",
		"desktopMenuTitle" : "sw 9/6/2000 05:26",
		"dictionaryOfPreferences" : "tfel 5/26/2012 01:05",
		"dictionaryOfPreferences:" : "rr 10/1/2005 15:14",
		"diffsInChangeList" : "",
		"diffsWithPrettyPrint" : "",
		"disable:" : "sw 4/12/2001 23:29",
		"disableGently:" : "sw 1/19/2000 13:51",
		"disableProgrammerFacilities" : "nk 7/30/2004 21:45",
		"dismissAllOnOptionClose" : "",
		"displaySizeChanged" : "ar 7/21/2010 20:20",
		"doesNotUnderstand:" : "sw 11/11/1998 11:40",
		"dragNDropWithAnimation" : "",
		"dropProducesWatcher" : "",
		"duplicateAllControlAndAltKeys" : "",
		"duplicateControlAndAltKeys" : "",
		"eToyFriendly" : "",
		"eToyFriendlyChanged" : "sw 4/12/2001 01:31",
		"eToyLoginEnabled" : "",
		"easySelection" : "",
		"editAnnotations" : "sw 6/13/2001 19:40",
		"editCustomHalos" : "ar 9/27/2005 20:32",
		"enable:" : "sw 4/12/2001 23:29",
		"enableGently:" : "sw 1/19/2000 13:53",
		"enableLocalSave" : "",
		"enableOrDisable:asPer:" : "sw 8/12/2000 01:26",
		"enableProgrammerFacilities" : "sw 6/29/1999 13:55",
		"enableProjectNavigator" : "sw 7/13/2001 21:34",
		"expandedPublishing" : "",
		"expungeParameter:" : "sw 5/16/2003 00:27",
		"extraDebuggerButtons" : "",
		"extractFlashInHighQuality" : "",
		"extractFlashInHighestQuality" : "",
		"fastDragWindowForMorphic" : "",
		"fenceEnabled" : "",
		"fenceSoundEnabled" : "",
		"fenceSoundEnabled:" : "mir 6/7/2002 17:10",
		"fontConfigurationMenu" : "jmv 8/6/2009 08:52",
		"fontFactor" : "dgd 3/25/2003 19:58",
		"fullScreenLeavesDeskMargins" : "",
		"generalizedYellowButtonMenu" : "",
		"giveHelpWithPreferences" : "nice 12/27/2009 03:11",
		"gradientMenu" : "",
		"gradientScrollBars" : "",
		"haloEnclosesFullBounds" : "",
		"haloSpecifications" : "sw 10/30/2000 13:32",
		"haloSpecificationsForWorld" : "dgd 10/21/2004 12:17",
		"haloTheme" : "",
		"haloTransitions" : "",
		"higherPerformance" : "",
		"honorDesktopCmdKeys" : "",
		"iconicHaloSpecifications" : "sw 12/29/2004 22:16",
		"iconicHalosInForce" : "hpt 9/24/2004 23:34",
		"ignoreStyleIfOnlyBold" : "",
		"includeSoundControlInNavigator" : "",
		"infiniteUndo" : "",
		"infiniteUndoChanged" : "sw 4/12/2001 01:32",
		"initialExtent" : "md 2/24/2006 21:26",
		"initialize" : "tfel 5/26/2012 01:04",
		"initializeDictionaryOfPreferences" : "rr 10/1/2005 15:14",
		"initializeParameters" : "sw 9/7/1999 12:45",
		"initializeTextHighlightingParameters" : "lr 7/12/2006 09:42",
		"inlineServicesInMenu" : "",
		"insertionPointColor" : "sw 9/7/1999 12:53",
		"insertionPointColor:" : "sw 9/7/1999 12:54",
		"inspectParameters" : "sw 1/24/2001 21:44",
		"inspectPreferences" : "rr 10/1/2005 15:14",
		"installBrightWindowColors" : "sw 2/26/2002 13:56",
		"installClassicHaloSpecs" : "sw 1/28/2000 10:35",
		"installCustomHaloSpecs" : "sw 1/28/2000 10:36",
		"installHaloSpecsFromArray:" : "nice 12/27/2009 03:11",
		"installHaloTheme:" : "hpt 9/24/2004 23:35",
		"installIconicHaloSpecs" : "sw 1/28/2000 10:36",
		"installMissingWindowColors" : "nice 12/27/2009 03:11",
		"installPastelWindowColors" : "bp 1/8/2011 13:00",
		"installSimpleHaloSpecs" : "sw 1/28/2000 10:36",
		"installTheme:" : "yo 7/2/2004 19:44",
		"installUniformWindowColors" : "laza 4/26/2010 10:22",
		"installWindowColorsVia:" : "tfel 5/26/2012 01:06",
		"keepTickingWhilePainting" : "",
		"keyboardFocusColor" : "dew 1/8/2002 01:07",
		"keyboardFocusColor:" : "sw 12/7/2001 00:44",
		"largeTilesSettingToggled" : "em 3/24/2005 15:34",
		"letUserPersonalizeMenu" : "ar 9/27/2005 20:32",
		"lightenStandardWindowPreferences" : "hpt 12/8/2004 19:35",
		"listOfCategories" : "tfel 5/26/2012 01:43",
		"loadPreferencesFrom:" : "ul 12/12/2009 14:07",
		"localeChanged" : "tak 8/3/2005 21:17",
		"logDebuggerStackToFile" : "",
		"magicHalos" : "",
		"maintainHalos" : "",
		"maxBalloonHelpLineLength" : "sw 11/5/1998 16:49",
		"menuAppearance3d" : "",
		"menuBorderColor" : "di 1/14/1999 20:16",
		"menuBorderWidth" : "sw 11/3/1998 11:16",
		"menuButtonInToolPane" : "",
		"menuColor" : "di 1/14/1999 20:17",
		"menuColorFromWorld" : "",
		"menuColorString" : "dgd 9/21/2003 13:51",
		"menuKeyboardControl" : "",
		"menuLineColor" : "dgd 3/23/2003 11:06",
		"menuSelectionColor" : "dgd 8/30/2004 20:59",
		"menuTitleBorderColor" : "di 1/14/1999 20:19",
		"menuTitleBorderWidth" : "sw 11/3/1998 11:16",
		"menuTitleColor" : "di 1/14/1999 20:18",
		"menuWithIcons" : "",
		"messengersInViewers" : "sw 8/11/2002 02:18",
		"metaMenuDisabled" : "sw 8/18/2000 13:26",
		"modalColorPickers" : "",
		"mouseOverForKeyboardFocus" : "",
		"mouseOverHalos" : "",
		"mouseOverHalosChanged" : "mir 9/12/2001 15:15",
		"multipleTextUndo" : "",
		"mvcProjectsAllowed" : "",
		"navigatorOnLeftEdge" : "",
		"navigatorShowingString" : "dgd 8/31/2003 18:03",
		"noviceMode" : "",
		"noviceModeSettingChanged" : "bp 1/8/2011 12:59",
		"offerThemesMenu" : "em 3/24/2005 14:11",
		"okToReinitializeFlaps" : "",
		"okayToChangeProjectLocalnessOf:" : "sw 4/24/2001 12:02",
		"oliveHandleForScriptedObjects" : "",
		"optionalButtons" : "",
		"optionalButtonsChanged" : "sw 6/12/2001 20:18",
		"outOfTheBox" : "sw 4/21/2002 07:37",
		"parameterAt:" : "sw 1/27/2000 23:02",
		"parameterAt:default:" : "sw 9/28/2001 08:52",
		"parameterAt:ifAbsent:" : "sw 2/7/2001 14:37",
		"parameterAt:ifAbsentPut:" : "sw 9/28/2001 08:40",
		"passwordsOnPublish" : "",
		"personal" : "sw 5/2/2002 10:45",
		"personalizeUserMenu:" : "wiz 2/20/2006 20:33",
		"personalizedWorldMenu" : "",
		"postscriptStoredAsEPS" : "",
		"prefEvent:" : "nice 12/27/2009 03:11",
		"preference:category:description:type:" : "ar 8/9/2009 15:14",
		"preferenceAt:" : "rr 10/1/2005 15:14",
		"preferenceAt:ifAbsent:" : "rr 10/1/2005 15:14",
		"preferenceObjectsInCategory:" : "ar 8/9/2009 15:20",
		"preferencesPanelWindowColor" : "",
		"preserveCommandExcursions" : "sw 8/29/2000 15:01",
		"preserveTrash" : "",
		"printStandardSystemFonts" : "nk 9/1/2004 11:37",
		"projectViewsInWindows" : "",
		"projectZoom" : "",
		"projectsSentToDisk" : "",
		"promptForUpdateServer" : "",
		"propertySheetFromHalo" : "",
		"purgeUndoOnQuit" : "",
		"readDocumentAtStartup" : "",
		"readOnlyMode" : "",
		"refreshFontSettings" : "nk 7/18/2004 15:34",
		"registerForEvents" : "nice 12/27/2009 03:11",
		"removeObsolete" : "ar 9/27/2005 21:49",
		"removePreference:" : "rr 10/1/2005 15:14",
		"removePreferencesFor:" : "ar 3/9/2009 21:41",
		"resetHaloSpecifications" : "sw 1/25/2000 20:10",
		"restartAlsoProceeds" : "",
		"restoreDefaultFonts" : "ul 11/25/2010 23:37",
		"restoreDefaultFontsForJapanese" : "yo 7/28/2004 21:25",
		"restoreDefaultMenuParameters" : "dgd 3/23/2003 11:11",
		"restoreFontsAfter:" : "ar 7/21/2010 20:13",
		"restorePersonalPreferences" : "ul 12/12/2009 14:07",
		"restorePreferencesFromDisk" : "nk 11/17/2002 12:07",
		"reverseWindowStagger" : "",
		"roundedCornersString" : "yo 2/10/2005 16:15",
		"roundedMenuCorners" : "",
		"roundedWindowCorners" : "",
		"roundedWindowCornersChanged" : "sw 4/12/2001 01:11",
		"savePersonalPreferences" : "rr 10/1/2005 15:14",
		"scrollBarColor" : "",
		"scrollBarWidth" : "",
		"scrollBarsNarrow" : "",
		"scrollBarsOnRight" : "",
		"scrollBarsWithoutMenuButton" : "",
		"securityChecksEnabled" : "",
		"selectiveHalos" : "",
		"serverMode" : "al 7/31/2007 16:17",
		"setArrowheads" : "sw 3/2/2004 22:11",
		"setBalloonHelpFontTo:" : "bp 6/13/2004 17:46",
		"setButtonFontTo:" : "sw 12/8/1999 22:06",
		"setCodeFontTo:" : "sw 7/25/2004 17:26",
		"setDefaultAnnotationInfo" : "sw 2/17/1999 00:41",
		"setDefaultFonts:" : "ar 9/7/2009 15:00",
		"setDemoFonts" : "md 3/7/2006 10:27",
		"setEToysFontTo:" : "dgd 7/12/2003 11:52",
		"setEToysTitleFontTo:" : "dgd 11/3/2004 15:03",
		"setFlag:toValue:during:" : "sw 1/4/2001 06:56",
		"setFlapsFontTo:" : "sw 12/8/1999 18:15",
		"setHaloLabelFontTo:" : "mir 8/24/2004 12:34",
		"setListFontTo:" : "dtl 2/12/2010 22:21",
		"setMenuFontTo:" : "ar 8/6/2009 18:30",
		"setNotificationParametersForStandardPreferences" : "nice 12/27/2009 03:11",
		"setPaintBoxButtonFontTo:" : "yo 1/12/2005 22:43",
		"setParameter:to:" : "stp 01/13/2000 13:29",
		"setPreference:toValue:" : "sw 4/12/2001 23:29",
		"setPreferencesFrom:" : "sw 4/21/2002 05:13",
		"setSystemFontTo:" : "sw 4/17/2001 11:34",
		"setWindowColorFor:to:" : "tfel 5/26/2012 01:08",
		"setWindowTitleFontTo:" : "dtl 2/10/2010 22:52",
		"sharedFlapsSettingChanged" : "sw 4/30/2001 20:39",
		"showAdvancedNavigatorButtons" : "",
		"showBoundsInHalo" : "",
		"showChooseGraphicHaloHandle" : "sw 11/6/2000 10:02",
		"showDeprecationWarnings" : "",
		"showDirectionForSketches" : "",
		"showDirectionHandles" : "",
		"showFlapsWhenPublishing" : "",
		"showProjectNavigator" : "",
		"showProjectNavigatorChanged" : "sw 4/12/2001 01:33",
		"showSecurityStatus" : "",
		"showSharedFlaps" : "",
		"showSplitterHandles" : "",
		"signProjectFiles" : "",
		"simpleFullHaloSpecifications" : "sw 7/28/2004 16:26",
		"simpleHalosInForce" : "hpt 9/24/2004 23:34",
		"simpleMenus" : "",
		"slideDismissalsToTrash" : "",
		"smallLand" : "dgd 3/12/2006 12:52",
		"smallLandBigFonts" : "dgd 11/3/2004 15:06",
		"smallLandFonts" : "dgd 7/28/2005 11:11",
		"smallLandPreferences" : "rss 8/23/2009 11:02",
		"smallLandSmallFonts" : "dgd 11/3/2004 15:04",
		"smallLandTinyFonts" : "dgd 7/28/2005 12:35",
		"smartUpdating" : "",
		"smartUpdatingChanged" : "sw 4/12/2001 01:30",
		"soundEnablingString" : "dgd 10/17/2003 12:14",
		"soundQuickStart" : "",
		"soundStopWhenDone" : "",
		"soundsEnabled" : "",
		"staggerPolicyString" : "dgd 9/21/2003 13:46",
		"standaloneSecurityChecksEnabled" : "mir 11/10/2003 14:28",
		"standardBalloonHelpFont" : "bp 6/13/2004 17:19",
		"standardButtonFont" : "sw 12/8/1999 16:13",
		"standardCodeFont" : "sw 12/8/1999 16:58",
		"standardDefaultTextFont" : "bp 6/13/2004 17:24",
		"standardEToysFont" : "nk 7/12/2003 08:50",
		"standardEToysTitleFont" : "dgd 11/3/2004 15:02",
		"standardFlapFont" : "sw 12/8/1999 16:13",
		"standardHaloLabelFont" : "mir 8/24/2004 12:34",
		"standardListFont" : "sw 12/8/1999 16:09",
		"standardMenuFont" : "sw 12/8/1999 16:58",
		"standardPaintBoxButtonFont" : "yo 1/12/2005 22:40",
		"standardSystemFont" : "tween 8/4/2007 14:30",
		"startInUntrustedDirectory" : "",
		"storePreferencesIn:" : "laza 4/7/2010 19:00",
		"storePreferencesToDisk" : "nk 11/17/2002 12:08",
		"subPixelRenderColorFonts" : "jmv 8/5/2009 23:11",
		"subPixelRenderFonts" : "jmv 8/5/2009 23:11",
		"suppressWindowTitlesInInstanceBrowsers" : "sw 11/15/2001 08:37",
		"swapControlAndAltKeys" : "",
		"swapMouseButtons" : "",
		"syntaxHighlightingAsYouType" : "",
		"syntaxHighlightingAsYouTypeAnsiAssignment" : "",
		"syntaxHighlightingAsYouTypeLeftArrowAssignment" : "",
		"systemWindowEmbedOK" : "",
		"tabAmongFields" : "",
		"textHighlightColor" : "sw 9/7/1999 12:53",
		"textHighlightColor:" : "sw 9/7/1999 12:54",
		"themeChoiceButtonOfColor:font:" : "dgd 9/1/2003 11:43",
		"thoroughSenders" : "",
		"tileTranslucentDrag" : "",
		"timeStampsInMenuTitles" : "",
		"tinyDisplay" : "",
		"toggleMenuColorPolicy" : "sw 7/13/1999 16:51",
		"togglePreference:" : "hpt 9/26/2004 16:50",
		"toggleRoundedCorners" : "sw 7/13/1999 16:52",
		"toggleSoundEnabling" : "ssa 2/9/2000 11:01",
		"toggleWindowPolicy" : "sw 6/11/1999 20:49",
		"traceMessages" : "",
		"turnOffPowerManager" : "",
		"twentyFourHourFileStamps" : "",
		"typeCheckingInTileScripting" : "",
		"uniTilesClassic" : "",
		"uniformWindowColor" : "laza 4/26/2010 10:22",
		"uniqueNamesInHalos" : "",
		"universalTiles" : "",
		"universalTilesSettingToggled" : "sw 4/13/2001 11:22",
		"unlimitedPaintArea" : "",
		"unload" : "asm 4/11/2003 12:38",
		"updateFromServerAtStartup" : "",
		"updateSavesFile" : "",
		"upgradeIsMerge" : "",
		"useButtonProprtiesToFire" : "",
		"useCategoryListsInViewers" : "sw 2/16/1999 11:24",
		"useFormsInPaintBox:" : "yo 1/13/2005 11:05",
		"useLocale" : "",
		"useOnlyServicesInMenu" : "",
		"useServicesInBrowserButtonBar" : "",
		"useSmartLabels" : "",
		"useUndo" : "",
		"useVectorVocabulary" : "",
		"valueOfFlag:" : "hpt 9/26/2004 16:49",
		"valueOfFlag:ifAbsent:" : "hpt 9/26/2004 16:48",
		"valueOfPreference:" : "hpt 9/26/2004 16:49",
		"valueOfPreference:ifAbsent:" : "hpt 9/26/2004 16:49",
		"vectorVocabularySettingChanged" : "sw 7/10/2005 03:06",
		"viewersInFlaps" : "",
		"visualExplorer" : "",
		"wantsChangeSetLogging" : "tfel 5/26/2012 01:04",
		"warnAboutInsecureContent" : "",
		"warnIfNoChangesFile" : "",
		"warnIfNoSourcesFile" : "",
		"windowColorFor:" : "sd 9/14/2006 20:13",
		"windowColorHelp" : "tfel 2/27/2010 19:34",
		"windowColorPreferenceForClassNamed:" : "tfel 5/26/2012 01:07",
		"windowColorTable" : "tfel 5/26/2012 01:05",
		"windowTitleFont" : "sw 12/8/1999 16:10",
		"windowTitleStyle" : "sw 12/8/1999 22:18",
		"wordStyleCursorMovement" : "" },
	"instance" : {
		 } }
