{
	"class" : {
		"on:with:calledBy:reopens:" : "BD 7/1/2018 17:18" },
	"instance" : {
		"buildButtonsWith:" : "BD 7/6/2018 10:38",
		"buildDescriptionWith:" : "BD 7/5/2018 22:02",
		"buildWindowWith:" : "LS 6/29/2018 16:28",
		"buildWith:" : "BD 7/6/2018 10:44",
		"buttonHeight" : "LS 6/29/2018 16:47",
		"buttons" : "BD 7/6/2018 10:31",
		"buttonsBottom" : "LS 6/29/2018 16:46",
		"buttonsFrame" : "LS 6/29/2018 16:44",
		"buttonsLeft" : "LS 6/29/2018 16:46",
		"buttonsOffsetTop" : "LS 6/29/2018 16:45",
		"buttonsRight" : "LS 6/29/2018 16:45",
		"buttonsTop" : "LS 6/29/2018 16:46",
		"calculateResultWeight:" : "BD 7/1/2018 12:53",
		"callingDialog" : "BD 7/1/2018 17:16",
		"callingDialog:" : "BD 7/3/2018 12:15",
		"callingWindow" : "BD 7/1/2018 14:26",
		"callingWindow:" : "BD 7/3/2018 12:15",
		"classesSelected" : "LS 6/29/2018 16:15",
		"classesSelected:" : "LS 6/29/2018 16:15",
		"close" : "BD 7/6/2018 10:51",
		"environment" : "LG 7/5/2018 19:59",
		"environment:" : "BD 7/6/2018 10:36",
		"initialExtent" : "BD 7/6/2018 10:29",
		"initialize" : "BD 7/5/2018 22:16",
		"lintingEnabled" : "BD 7/6/2018 09:42",
		"lintingEnabled:" : "BD 7/6/2018 09:43",
		"open" : "LS 6/29/2018 16:34",
		"openResultsDialog" : "LG 7/5/2018 20:26",
		"reactToChange:" : "BD 7/5/2018 22:44",
		"resultCount" : "BD 7/6/2018 10:30",
		"resultDialog" : "BD 7/1/2018 12:23",
		"resultDialog:" : "BD 7/3/2018 12:18",
		"resultsFrame" : "BD 7/3/2018 12:17",
		"run" : "LG 7/5/2018 20:27",
		"testsSelected" : "LS 6/29/2018 16:15",
		"testsSelected:" : "LS 6/29/2018 16:15",
		"toOverview" : "BD 7/3/2018 12:15",
		"toggleAutoLint" : "BD 7/6/2018 10:37",
		"toggleAutoLintDescription" : "BD 7/6/2018 10:37",
		"toggleAutoLintState" : "BD 7/5/2018 22:39",
		"toggleButton" : "BD 7/5/2018 22:16",
		"toggleButton:" : "BD 7/5/2018 22:16",
		"windowTitle" : "BD 7/3/2018 12:15" } }
