{
	"class" : {
		"createOrCancel:" : "ct 12/12/2024 02:19",
		"edit:" : "ct 12/12/2024 03:45" },
	"instance" : {
		"accept" : "ct 12/12/2024 03:05",
		"acceptColor" : "ct 12/12/2024 03:03",
		"accepted" : "ct 12/12/2024 03:06",
		"allClasses" : "ct 12/12/2024 03:00",
		"allClasses:" : "ct 12/12/2024 03:00",
		"allSystemCategories" : "ct 12/12/2024 02:39",
		"allSystemCategories:" : "ct 12/12/2024 02:59",
		"aspectDependencies" : "ct 12/12/2024 03:31",
		"availableClasses" : "ct 12/17/2024 22:09",
		"availableSystemCategories" : "ct 12/12/2024 02:38",
		"buildButtons:" : "ct 12/12/2024 02:21",
		"buildClassList:" : "ct 12/12/2024 03:16",
		"buildCreateDialogWith:" : "ct 12/12/2024 02:20",
		"buildEditDialogWith:" : "ct 12/12/2024 03:46",
		"buildSystemCategoryList:" : "ct 12/12/2024 03:16",
		"cancel" : "ct 12/12/2024 03:05",
		"cancelColor" : "ct 12/12/2024 03:03",
		"changed:" : "ct 2/8/2022 14:49",
		"changedDependent:" : "ct 2/8/2022 14:49",
		"class:select:" : "ct 12/12/2024 05:53",
		"classAt:select:" : "ct 12/12/2024 03:33",
		"classesInSystemCategory:" : "ct 12/12/2024 04:43",
		"close:" : "ct 12/12/2024 03:05",
		"createOrCancel:" : "ct 12/12/2024 03:38",
		"dependentAspectsOn:" : "ct 2/8/2022 14:49",
		"edit:" : "ct 12/12/2024 03:46",
		"hasClassSelected:" : "ct 12/12/2024 03:06",
		"hasClassSelectedAt:" : "ct 12/12/2024 03:04",
		"hasSystemCategorySelected:" : "ct 12/12/2024 03:14",
		"hasSystemCategorySelectedAt:" : "ct 12/12/2024 03:14",
		"initialize" : "ct 12/12/2024 03:07",
		"initializeWithSystemOrganizer:" : "ct 12/18/2024 22:39",
		"selectClass:" : "ct 12/12/2024 03:33",
		"selectClassAt:" : "ct 12/12/2024 03:32",
		"selectSystemCategory:" : "ct 12/12/2024 03:23",
		"selectSystemCategoryAt:" : "ct 12/12/2024 03:23",
		"selectedClass" : "ct 12/12/2024 03:02",
		"selectedClassIndex" : "ct 12/12/2024 03:02",
		"selectedClasses" : "ct 12/12/2024 03:39",
		"selectedClasses:" : "ct 12/12/2024 03:50",
		"selectedSystemCategories" : "ct 12/12/2024 03:39",
		"selectedSystemCategory" : "ct 12/12/2024 02:46",
		"selectedSystemCategoryIndex" : "ct 12/12/2024 02:48",
		"systemCategory:select:" : "ct 12/12/2024 05:53",
		"systemCategoryAt:select:" : "ct 12/12/2024 03:25",
		"systemOrganizer" : "ct 12/12/2024 02:58",
		"systemOrganizer:" : "ct 12/12/2024 02:58",
		"target" : "ct 12/12/2024 03:37",
		"target:" : "ct 12/12/2024 03:37",
		"targetClass" : "ct 12/12/2024 03:37" } }
